{
  "project_info": {
    "project_number": "388633377698",
    "project_id": "crashlab-f8e90",
    "storage_bucket": "crashlab-f8e90.firebasestorage.app"
  },
  "client": [
    {
      "client_info": {
        "mobilesdk_app_id": "1:388633377698:android:578c27daf5ad78f8d3d0fb",
        "android_client_info": {
          "package_name": "com.aincrad.crashlab"
        }
      },
      "oauth_client": [],
      "api_key": [
        {
          "current_key": "AIzaSyCsU7EmbRTI2kNEStPbMjqrctwyYE7q4oE"
        }
      ],
      "services": {
        "appinvite_service": {
          "other_platform_oauth_client": []
        }
      }
    }
  ],
  "configuration_version": "1"
}